datasette_connectors/__init__.py
datasette_connectors/cli.py
datasette_connectors/connection.py
datasette_connectors/connectors.py
datasette_connectors/cursor.py
datasette_connectors/monkey.py
datasette_connectors/row.py
datasette_connectors-2.0.1.dist-info/LICENSE
datasette_connectors-2.0.1.dist-info/METADATA
datasette_connectors-2.0.1.dist-info/WHEEL
datasette_connectors-2.0.1.dist-info/entry_points.txt
datasette_connectors-2.0.1.dist-info/top_level.txt
datasette_connectors-2.0.1.dist-info/RECORD
