Metadata-Version: 2.1
Name: datasette-connectors
Version: 2.0.1
Summary: Datasette support to other database types
Home-page: https://github.com/pytables/datasette-connectors
Author: Javier Sancho
Author-email: jsf@jsancho.org
License: Apache License, Version 2.0
Platform: UNKNOWN
Requires-Dist: datasette (==0.51.1)
